Metadata-Version: 1.2
Name: fipibar
Version: 0.0.7
Summary: Fip radio plugin for Polybar
Home-page: https://github.com/conor-f/fipibar
License: UNKNOWN
Platform: UNKNOWN
Requires-Python: >=3.6
